conflict_zone_extractor/__init__.py
conflict_zone_extractor/main.py
conflict_zone_extractor/prompts.py
conflict_zone_extractor-2025.12.21180055.dist-info/METADATA
conflict_zone_extractor-2025.12.21180055.dist-info/WHEEL
conflict_zone_extractor-2025.12.21180055.dist-info/top_level.txt
conflict_zone_extractor-2025.12.21180055.dist-info/RECORD
