Metadata-Version: 2.4
Name: conflict-zone-extractor
Version: 2025.12.21180055
Summary: A new package that processes text input describing volunteer activities in conflict zones, such as reports of volunteers physically intervening between Israeli settlers and Palestinian villages. It us
Author-email: conflict-zone-extractor <hi@eugene.plus>
License: MIT
Project-URL: Homepage, https://github.com/chigwell/conflict-zone-extractor
Requires-Python: >=3.9
Requires-Dist: langchain-llm7>=0.0.0
Requires-Dist: llmatch-messages>=0.0.0
Requires-Dist: langchain-core>=0.3.0
